{
	"kind" : "toolchains",
	"toolchains" : 
	[
		{
			"compiler" : 
			{
				"id" : "GNU",
				"implicit" : 
				{
					"includeDirectories" : 
					[
<<<<<<<< HEAD:2/build/.cmake/api/v1/reply/toolchains-v1-1cf14f459b4b1a3144ab.json
						"E:/MinGW64/lib/gcc/x86_64-w64-mingw32/13.1.0/include",
						"E:/MinGW64/include",
						"E:/MinGW64/lib/gcc/x86_64-w64-mingw32/13.1.0/include-fixed",
						"E:/MinGW64/x86_64-w64-mingw32/include"
					],
					"linkDirectories" : 
					[
						"E:/MinGW64/lib/gcc/x86_64-w64-mingw32/13.1.0",
						"E:/MinGW64/lib/gcc",
						"E:/MinGW64/x86_64-w64-mingw32/lib",
						"E:/MinGW64/lib"
========
						"D:/MinGW64/lib/gcc/x86_64-w64-mingw32/13.1.0/include",
						"D:/MinGW64/include",
						"D:/MinGW64/lib/gcc/x86_64-w64-mingw32/13.1.0/include-fixed",
						"D:/MinGW64/x86_64-w64-mingw32/include",
						"/MinGW/include"
					],
					"linkDirectories" : 
					[
						"D:/MinGW64/lib/gcc/x86_64-w64-mingw32/13.1.0",
						"D:/MinGW64/lib/gcc",
						"D:/MinGW64/x86_64-w64-mingw32/lib",
						"D:/MinGW64/lib",
						"/MinGW/lib"
>>>>>>>> 4b3bd5e98fd2adf1f537cb6e569d81e8a85720f7:2/build/.cmake/api/v1/reply/toolchains-v1-df6e9fb8880cecc42f9a.json
					],
					"linkFrameworkDirectories" : [],
					"linkLibraries" : 
					[
						"mingw32",
						"gcc",
						"moldname",
						"mingwex",
						"kernel32",
						"mcfgthread",
						"kernel32",
						"ntdll",
						"advapi32",
						"shell32",
						"user32",
						"kernel32",
						"mingw32",
						"gcc",
						"moldname",
						"mingwex",
						"kernel32",
						"mcfgthread",
						"kernel32",
						"ntdll"
					]
				},
<<<<<<<< HEAD:2/build/.cmake/api/v1/reply/toolchains-v1-1cf14f459b4b1a3144ab.json
				"path" : "E:/MinGW64/bin/gcc.exe",
========
				"path" : "D:/MinGW64/bin/gcc.exe",
>>>>>>>> 4b3bd5e98fd2adf1f537cb6e569d81e8a85720f7:2/build/.cmake/api/v1/reply/toolchains-v1-df6e9fb8880cecc42f9a.json
				"version" : "13.1.0"
			},
			"language" : "C",
			"sourceFileExtensions" : 
			[
				"c",
				"m"
			]
		},
		{
			"compiler" : 
			{
				"id" : "GNU",
				"implicit" : 
				{
					"includeDirectories" : 
					[
<<<<<<<< HEAD:2/build/.cmake/api/v1/reply/toolchains-v1-1cf14f459b4b1a3144ab.json
						"E:/MinGW64/include/c++/13.1.0",
						"E:/MinGW64/include/c++/13.1.0/x86_64-w64-mingw32",
						"E:/MinGW64/include/c++/13.1.0/backward",
						"E:/MinGW64/lib/gcc/x86_64-w64-mingw32/13.1.0/include",
						"E:/MinGW64/include",
						"E:/MinGW64/lib/gcc/x86_64-w64-mingw32/13.1.0/include-fixed",
						"E:/MinGW64/x86_64-w64-mingw32/include"
					],
					"linkDirectories" : 
					[
						"E:/MinGW64/lib/gcc/x86_64-w64-mingw32/13.1.0",
						"E:/MinGW64/lib/gcc",
						"E:/MinGW64/x86_64-w64-mingw32/lib",
						"E:/MinGW64/lib"
========
						"D:/MinGW64/include/c++/13.1.0",
						"D:/MinGW64/include/c++/13.1.0/x86_64-w64-mingw32",
						"D:/MinGW64/include/c++/13.1.0/backward",
						"D:/MinGW64/lib/gcc/x86_64-w64-mingw32/13.1.0/include",
						"D:/MinGW64/include",
						"D:/MinGW64/lib/gcc/x86_64-w64-mingw32/13.1.0/include-fixed",
						"D:/MinGW64/x86_64-w64-mingw32/include",
						"/MinGW/include"
					],
					"linkDirectories" : 
					[
						"D:/MinGW64/lib/gcc/x86_64-w64-mingw32/13.1.0",
						"D:/MinGW64/lib/gcc",
						"D:/MinGW64/x86_64-w64-mingw32/lib",
						"D:/MinGW64/lib",
						"/MinGW/lib"
>>>>>>>> 4b3bd5e98fd2adf1f537cb6e569d81e8a85720f7:2/build/.cmake/api/v1/reply/toolchains-v1-df6e9fb8880cecc42f9a.json
					],
					"linkFrameworkDirectories" : [],
					"linkLibraries" : 
					[
						"stdc++",
						"mingw32",
						"gcc_s",
						"gcc",
						"moldname",
						"mingwex",
						"kernel32",
						"mcfgthread",
						"kernel32",
						"ntdll",
						"advapi32",
						"shell32",
						"user32",
						"kernel32",
						"mingw32",
						"gcc_s",
						"gcc",
						"moldname",
						"mingwex",
						"kernel32",
						"mcfgthread",
						"kernel32",
						"ntdll"
					]
				},
<<<<<<<< HEAD:2/build/.cmake/api/v1/reply/toolchains-v1-1cf14f459b4b1a3144ab.json
				"path" : "E:/MinGW64/bin/g++.exe",
========
				"path" : "D:/MinGW64/bin/g++.exe",
>>>>>>>> 4b3bd5e98fd2adf1f537cb6e569d81e8a85720f7:2/build/.cmake/api/v1/reply/toolchains-v1-df6e9fb8880cecc42f9a.json
				"version" : "13.1.0"
			},
			"language" : "CXX",
			"sourceFileExtensions" : 
			[
				"C",
				"M",
				"c++",
				"cc",
				"cpp",
				"cxx",
				"mm",
				"mpp",
				"CPP",
				"ixx",
				"cppm"
			]
		},
		{
			"compiler" : 
			{
				"implicit" : {},
<<<<<<<< HEAD:2/build/.cmake/api/v1/reply/toolchains-v1-1cf14f459b4b1a3144ab.json
				"path" : "E:/MinGW64/bin/windres.exe"
========
				"path" : "D:/MinGW64/bin/windres.exe"
>>>>>>>> 4b3bd5e98fd2adf1f537cb6e569d81e8a85720f7:2/build/.cmake/api/v1/reply/toolchains-v1-df6e9fb8880cecc42f9a.json
			},
			"language" : "RC",
			"sourceFileExtensions" : 
			[
				"rc",
				"RC"
			]
		}
	],
	"version" : 
	{
		"major" : 1,
		"minor" : 0
	}
}
